[
  {
    "result": 1,
    "cur_unit": "AED",
    "ttb": "406",
    "tts": "414.21",
    "deal_bas_r": "410.11",
    "bkpr": "410",
    "yy_efee_r": "0",
    "ten_dd_efee_r": "0",
    "kftc_bkpr": "410",
    "kftc_deal_bas_r": "410.11",
    "cur_nm": "아랍에미리트 디르함"
  },
  {
    "result": 1,
    "cur_unit": "AUD",
    "ttb": "1,027.68",
    "tts": "1,048.45",
    "deal_bas_r": "1,038.07",
    "bkpr": "1,038",
    "yy_efee_r": "0",
    "ten_dd_efee_r": "0",
    "kftc_bkpr": "1,038",
    "kftc_deal_bas_r": "1,038.07",
    "cur_nm": "호주 달러"
  },
  {
    "result": 1,
    "cur_unit": "BHD",
    "ttb": "3,943.45",
    "tts": "4,023.12",
    "deal_bas_r": "3,983.29",
    "bkpr": "3,983",
    "yy_efee_r": "0",
    "ten_dd_efee_r": "0",
    "kftc_bkpr": "3,983",
    "kftc_deal_bas_r": "3,983.29",
    "cur_nm": "바레인 디나르"
  },
  {
    "result": 1,
    "cur_unit": "BND",
    "ttb": "1,160.15",
    "tts": "1,183.58",
    "deal_bas_r": "1,171.87",
    "bkpr": "1,171",
    "yy_efee_r": "0",
    "ten_dd_efee_r": "0",
    "kftc_bkpr": "1,171",
    "kftc_deal_bas_r": "1,171.87",
    "cur_nm": "브루나이 달러"
  },
  {
    "result": 1,
    "cur_unit": "CAD",
    "ttb": "1,076.55",
    "tts": "1,098.3",
    "deal_bas_r": "1,087.43",
    "bkpr": "1,087",
    "yy_efee_r": "0",
    "ten_dd_efee_r": "0",
    "kftc_bkpr": "1,087",
    "kftc_deal_bas_r": "1,087.43",
    "cur_nm": "캐나다 달러"
  },
  {
    "result": 1,
    "cur_unit": "CHF",
    "ttb": "1,876.7",
    "tts": "1,914.61",
    "deal_bas_r": "1,895.66",
    "bkpr": "1,895",
    "yy_efee_r": "0",
    "ten_dd_efee_r": "0",
    "kftc_bkpr": "1,895",
    "kftc_deal_bas_r": "1,895.66",
    "cur_nm": "스위스 프랑"
  },
  {
    "result": 1,
    "cur_unit": "CNH",
    "ttb": "215.91",
    "tts": "220.28",
    "deal_bas_r": "218.1",
    "bkpr": "218",
    "yy_efee_r": "0",
    "ten_dd_efee_r": "0",
    "kftc_bkpr": "218",
    "kftc_deal_bas_r": "218.1",
    "cur_nm": "위안화"
  },
  {
    "result": 1,
    "cur_unit": "DKK",
    "ttb": "230.25",
    "tts": "234.9",
    "deal_bas_r": "232.58",
    "bkpr": "232",
    "yy_efee_r": "0",
    "ten_dd_efee_r": "0",
    "kftc_bkpr": "232",
    "kftc_deal_bas_r": "232.58",
    "cur_nm": "덴마아크 크로네"
  },
  {
    "result": 1,
    "cur_unit": "EUR",
    "ttb": "1,720.55",
    "tts": "1,755.3",
    "deal_bas_r": "1,737.93",
    "bkpr": "1,737",
    "yy_efee_r": "0",
    "ten_dd_efee_r": "0",
    "kftc_bkpr": "1,737",
    "kftc_deal_bas_r": "1,737.93",
    "cur_nm": "유로"
  },
  {
    "result": 1,
    "cur_unit": "GBP",
    "ttb": "1,988.73",
    "tts": "2,028.9",
    "deal_bas_r": "2,008.82",
    "bkpr": "2,008",
    "yy_efee_r": "0",
    "ten_dd_efee_r": "0",
    "kftc_bkpr": "2,008",
    "kftc_deal_bas_r": "2,008.82",
    "cur_nm": "영국 파운드"
  },
  {
    "result": 1,
    "cur_unit": "HKD",
    "ttb": "190.55",
    "tts": "194.4",
    "deal_bas_r": "192.48",
    "bkpr": "192",
    "yy_efee_r": "0",
    "ten_dd_efee_r": "0",
    "kftc_bkpr": "192",
    "kftc_deal_bas_r": "192.48",
    "cur_nm": "홍콩 달러"
  },
  {
    "result": 1,
    "cur_unit": "IDR(100)",
    "ttb": "8.82",
    "tts": "8.99",
    "deal_bas_r": "8.91",
    "bkpr": "8",
    "yy_efee_r": "0",
    "ten_dd_efee_r": "0",
    "kftc_bkpr": "8",
    "kftc_deal_bas_r": "8.91",
    "cur_nm": "인도네시아 루피아"
  },
  {
    "result": 1,
    "cur_unit": "JPY(100)",
    "ttb": "934.03",
    "tts": "952.9",
    "deal_bas_r": "943.47",
    "bkpr": "943",
    "yy_efee_r": "0",
    "ten_dd_efee_r": "0",
    "kftc_bkpr": "943",
    "kftc_deal_bas_r": "943.47",
    "cur_nm": "일본 옌"
  },
  {
    "result": 1,
    "cur_unit": "KRW",
    "ttb": "0",
    "tts": "0",
    "deal_bas_r": "1",
    "bkpr": "1",
    "yy_efee_r": "0",
    "ten_dd_efee_r": "0",
    "kftc_bkpr": "1",
    "kftc_deal_bas_r": "1",
    "cur_nm": "한국 원"
  },
  {
    "result": 1,
    "cur_unit": "KWD",
    "ttb": "4,862.67",
    "tts": "4,960.9",
    "deal_bas_r": "4,911.79",
    "bkpr": "4,911",
    "yy_efee_r": "0",
    "ten_dd_efee_r": "0",
    "kftc_bkpr": "4,911",
    "kftc_deal_bas_r": "4,911.79",
    "cur_nm": "쿠웨이트 디나르"
  },
  {
    "result": 1,
    "cur_unit": "MYR",
    "ttb": "373.34",
    "tts": "380.89",
    "deal_bas_r": "377.12",
    "bkpr": "377",
    "yy_efee_r": "0",
    "ten_dd_efee_r": "0",
    "kftc_bkpr": "377",
    "kftc_deal_bas_r": "377.12",
    "cur_nm": "말레이지아 링기트"
  },
  {
    "result": 1,
    "cur_unit": "NOK",
    "ttb": "153.78",
    "tts": "156.89",
    "deal_bas_r": "155.34",
    "bkpr": "155",
    "yy_efee_r": "0",
    "ten_dd_efee_r": "0",
    "kftc_bkpr": "155",
    "kftc_deal_bas_r": "155.34",
    "cur_nm": "노르웨이 크로네"
  },
  {
    "result": 1,
    "cur_unit": "NZD",
    "ttb": "859.33",
    "tts": "876.7",
    "deal_bas_r": "868.02",
    "bkpr": "868",
    "yy_efee_r": "0",
    "ten_dd_efee_r": "0",
    "kftc_bkpr": "868",
    "kftc_deal_bas_r": "868.02",
    "cur_nm": "뉴질랜드 달러"
  },
  {
    "result": 1,
    "cur_unit": "SAR",
    "ttb": "397.46",
    "tts": "405.49",
    "deal_bas_r": "401.48",
    "bkpr": "401",
    "yy_efee_r": "0",
    "ten_dd_efee_r": "0",
    "kftc_bkpr": "401",
    "kftc_deal_bas_r": "401.48",
    "cur_nm": "사우디 리얄"
  },
  {
    "result": 1,
    "cur_unit": "SEK",
    "ttb": "158.24",
    "tts": "161.43",
    "deal_bas_r": "159.84",
    "bkpr": "159",
    "yy_efee_r": "0",
    "ten_dd_efee_r": "0",
    "kftc_bkpr": "159",
    "kftc_deal_bas_r": "159.84",
    "cur_nm": "스웨덴 크로나"
  },
  {
    "result": 1,
    "cur_unit": "SGD",
    "ttb": "1,160.15",
    "tts": "1,183.58",
    "deal_bas_r": "1,171.87",
    "bkpr": "1,171",
    "yy_efee_r": "0",
    "ten_dd_efee_r": "0",
    "kftc_bkpr": "1,171",
    "kftc_deal_bas_r": "1,171.87",
    "cur_nm": "싱가포르 달러"
  },
  {
    "result": 1,
    "cur_unit": "THB",
    "ttb": "45.38",
    "tts": "46.29",
    "deal_bas_r": "45.84",
    "bkpr": "45",
    "yy_efee_r": "0",
    "ten_dd_efee_r": "0",
    "kftc_bkpr": "45",
    "kftc_deal_bas_r": "45.84",
    "cur_nm": "태국 바트"
  },
  {
    "result": 1,
    "cur_unit": "USD",
    "ttb": "1,491.13",
    "tts": "1,521.26",
    "deal_bas_r": "1,506.2",
    "bkpr": "1,506",
    "yy_efee_r": "0",
    "ten_dd_efee_r": "0",
    "kftc_bkpr": "1,506",
    "kftc_deal_bas_r": "1,506.2",
    "cur_nm": "미국 달러"
  }
]
